quanbit/__init__.py
quanbit/circuit.py
quanbit/measure.py
quanbit/operators.py
quanbit-0.0.1.dist-info/LICENSE
quanbit-0.0.1.dist-info/METADATA
quanbit-0.0.1.dist-info/WHEEL
quanbit-0.0.1.dist-info/top_level.txt
quanbit-0.0.1.dist-info/RECORD
