Metadata-Version: 2.1
Name: quanbit
Version: 0.0.1
Summary: Python library for simulating quantum computor and algorithm.
Home-page: https://github.com/tczorro/quanbit
Author: Xiaotian Derrick Yang
Author-email: yxt1991@gmail.com
License: UNKNOWN
Platform: UNKNOWN
Requires-Dist: numpy (>=1.16)
Requires-Dist: pytest (>=2.6)
